geodantic/__init__.py
geodantic/base.py
geodantic/features.py
geodantic/geometries.py
geodantic/py.typed
geodantic/types.py
geodantic-0.4.0.dist-info/LICENSE
geodantic-0.4.0.dist-info/WHEEL
geodantic-0.4.0.dist-info/METADATA
geodantic-0.4.0.dist-info/RECORD
