Metadata-Version: 2.1
Name: geodantic
Version: 0.4.0
Summary: GeoJSON parsing and validation using Pydantic
Home-page: https://github.com/alexandermalyga/geodantic
License: MIT
Author: Alexander Malyga
Author-email: alexander@malyga.io
Requires-Python: >=3.12,<4.0
Classifier: Intended Audience :: Developers
Classifier: License :: OSI Approved :: MIT License
Classifier: Programming Language :: Python :: 3
Classifier: Programming Language :: Python :: 3.12
Classifier: Topic :: Software Development :: Libraries :: Python Modules
Classifier: Typing :: Typed
Requires-Dist: pydantic (>=2.0.3,<3.0.0)
Project-URL: Repository, https://github.com/alexandermalyga/geodantic
